openapi_client/__init__.py
openapi_client/api_client.py
openapi_client/configuration.py
openapi_client/rest.py
openapi_client/api/__init__.py
openapi_client/api/bunker_api.py
openapi_client/models/__init__.py
openapi_client/models/document.py
openapi_client/models/error_message.py
openapi_client/models/face.py
openapi_client/models/person.py
openapi_client/models/scan.py
test/__init__.py
test/test_bunker_api.py
test/test_document.py
test/test_error_message.py
test/test_face.py
test/test_person.py
test/test_scan.py
bunker-1.0.1.dist-info/METADATA
bunker-1.0.1.dist-info/WHEEL
bunker-1.0.1.dist-info/top_level.txt
bunker-1.0.1.dist-info/RECORD
