Metadata-Version: 2.1
Name: bunker
Version: 1.0.1
Summary: Bunker OpenAPI Specification
Home-page: https://github.com/bunker-ai
Author: Caio Pizzol
Author-email: caio@bunker.ai
License: UNKNOWN
Keywords: OpenAPI,OpenAPI-Generator,Bunker OpenAPI Specification
Platform: UNKNOWN
Requires-Dist: urllib3 (>=1.15)
Requires-Dist: six (>=1.10)
Requires-Dist: certifi
Requires-Dist: python-dateutil
